e3psi/__init__.py
e3psi/base.py
e3psi/distances.py
e3psi/graphs.py
e3psi/mincepy_types.py
e3psi/models.py
e3psi/provides.py
e3psi/version.py
e3psi-0.3.1.dist-info/entry_points.txt
e3psi-0.3.1.dist-info/LICENSE
e3psi-0.3.1.dist-info/WHEEL
e3psi-0.3.1.dist-info/METADATA
e3psi-0.3.1.dist-info/RECORD
