Metadata-Version: 2.1
Name: e3psi
Version: 0.3.1
Summary: Equivariant machine learning library for learning from electronic structures.
Keywords: machine learning,equivariant,electronic structure
Author-email: Martin Uhrin <martin.uhrin.10@ucl.ac.uk>
Requires-Python: >=3.7
Classifier: Development Status :: 5 - Production/Stable
Classifier: License :: OSI Approved :: GNU Lesser General Public License v3 or later (LGPLv3+)
Classifier: Operating System :: POSIX :: Linux
Classifier: Operating System :: MacOS :: MacOS X
Classifier: Programming Language :: Python
Classifier: Programming Language :: Python :: 3.7
Classifier: Programming Language :: Python :: 3.8
Classifier: Programming Language :: Python :: 3.9
Classifier: Programming Language :: Python :: 3.10
Classifier: Topic :: Scientific/Engineering
Requires-Dist: e3nn
Requires-Dist: matplotlib
Requires-Dist: mincepy[sci]
Requires-Dist: numpy
Requires-Dist: pandas
Requires-Dist: torch
Requires-Dist: black[d] ; extra == "dev"
Requires-Dist: flit ; extra == "dev"
Requires-Dist: pre-commit ; extra == "dev"
Requires-Dist: pytest ; extra == "dev"
Requires-Dist: pytest-cov ; extra == "dev"
Provides-Extra: dev
